{
	"id": "2020_20104_html",
	"school": "Architettura",
	"year": 2020,
	"phase": {
		"raw": "Architettura - Extra-ue - Seconda Graduatoria",
		"stripped": "Seconda Graduatoria",
		"primary": 0,
		"secondary": 2,
		"language": "IT",
		"isExtraEu": true
	},
	"courses": {},
	"rows": [
		{
			"id": "",
			"position": 1,
			"canEnroll": false,
			"courses": [],
			"result": 25.3,
			"sectionsResults": null,
			"ofa": {
				"ENG": true
			}
		},
		{
			"id": "",
			"position": 2,
			"canEnroll": true,
			"courses": [
				{
					"title": "Assegnato - PROGETTAZIONE DELL'ARCHITETTURA - TAUGHT IN ENGLISH",
					"location": "MI LEONARDO",
					"position": 0,
					"canEnroll": true
				}
			],
			"result": 25,
			"sectionsResults": null,
			"ofa": {
				"ENG": true
			}
		},
		{
			"id": "",
			"position": 3,
			"canEnroll": true,
			"courses": [
				{
					"title": "Assegnato - PROGETTAZIONE DELL'ARCHITETTURA - TAUGHT IN ENGLISH",
					"location": "MI LEONARDO",
					"position": 0,
					"canEnroll": true
				}
			],
			"result": 24.8,
			"sectionsResults": null,
			"ofa": {
				"ENG": true
			}
		},
		{
			"id": "",
			"position": 4,
			"canEnroll": true,
			"courses": [
				{
					"title": "Assegnato - PROGETTAZIONE DELL'ARCHITETTURA - TAUGHT IN ENGLISH",
					"location": "MI LEONARDO",
					"position": 0,
					"canEnroll": true
				}
			],
			"result": 24.5,
			"sectionsResults": null,
			"ofa": {
				"ENG": true
			}
		},
		{
			"id": "",
			"position": 5,
			"canEnroll": true,
			"courses": [
				{
					"title": "Assegnato - PROGETTAZIONE DELL'ARCHITETTURA - TAUGHT IN ENGLISH",
					"location": "MI LEONARDO",
					"position": 0,
					"canEnroll": true
				}
			],
			"result": 24.5,
			"sectionsResults": null,
			"ofa": {
				"ENG": true
			}
		},
		{
			"id": "",
			"position": 6,
			"canEnroll": false,
			"courses": [],
			"result": 24.5,
			"sectionsResults": null,
			"ofa": {
				"ENG": true
			}
		},
		{
			"id": "",
			"position": 7,
			"canEnroll": true,
			"courses": [
				{
					"title": "PROGETTAZIONE DELL'ARCHITETTURA",
					"location": "PIACENZA",
					"position": 0,
					"canEnroll": true
				}
			],
			"result": 24.4,
			"sectionsResults": null,
			"ofa": {
				"ENG": true
			}
		},
		{
			"id": "",
			"position": 8,
			"canEnroll": true,
			"courses": [
				{
					"title": "Assegnato - PROGETTAZIONE DELL'ARCHITETTURA - TAUGHT IN ENGLISH",
					"location": "PIACENZA",
					"position": 0,
					"canEnroll": true
				}
			],
			"result": 24.1,
			"sectionsResults": null,
			"ofa": {
				"ENG": true
			}
		},
		{
			"id": "",
			"position": 9,
			"canEnroll": true,
			"courses": [
				{
					"title": "Assegnato - PROGETTAZIONE DELL'ARCHITETTURA - TAUGHT IN ENGLISH",
					"location": "PIACENZA",
					"position": 0,
					"canEnroll": true
				}
			],
			"result": 23.6,
			"sectionsResults": null,
			"ofa": {
				"ENG": true
			}
		},
		{
			"id": "",
			"position": 10,
			"canEnroll": true,
			"courses": [
				{
					"title": "Assegnato - PROGETTAZIONE DELL'ARCHITETTURA - TAUGHT IN ENGLISH",
					"location": "PIACENZA",
					"position": 0,
					"canEnroll": true
				}
			],
			"result": 23.6,
			"sectionsResults": null,
			"ofa": {
				"ENG": true
			}
		},
		{
			"id": "",
			"position": 11,
			"canEnroll": true,
			"courses": [
				{
					"title": "Assegnato - PROGETTAZIONE DELL'ARCHITETTURA - TAUGHT IN ENGLISH",
					"location": "PIACENZA",
					"position": 0,
					"canEnroll": true
				}
			],
			"result": 23.3,
			"sectionsResults": null,
			"ofa": {
				"ENG": true
			}
		},
		{
			"id": "",
			"position": 12,
			"canEnroll": false,
			"courses": [],
			"result": 23.2,
			"sectionsResults": null,
			"ofa": {
				"ENG": true
			}
		},
		{
			"id": "",
			"position": 13,
			"canEnroll": false,
			"courses": [],
			"result": 23,
			"sectionsResults": null,
			"ofa": {
				"ENG": true
			}
		},
		{
			"id": "",
			"position": 14,
			"canEnroll": true,
			"courses": [
				{
					"title": "Assegnato - PROGETTAZIONE DELL'ARCHITETTURA - TAUGHT IN ENGLISH",
					"location": "PIACENZA",
					"position": 0,
					"canEnroll": true
				}
			],
			"result": 22.9,
			"sectionsResults": null,
			"ofa": {
				"ENG": true
			}
		},
		{
			"id": "",
			"position": 15,
			"canEnroll": true,
			"courses": [
				{
					"title": "Assegnato - PROGETTAZIONE DELL'ARCHITETTURA - TAUGHT IN ENGLISH",
					"location": "PIACENZA",
					"position": 0,
					"canEnroll": true
				}
			],
			"result": 22.6,
			"sectionsResults": null,
			"ofa": {
				"ENG": true
			}
		},
		{
			"id": "",
			"position": 16,
			"canEnroll": false,
			"courses": [],
			"result": 22.2,
			"sectionsResults": null,
			"ofa": {
				"ENG": true
			}
		},
		{
			"id": "",
			"position": 17,
			"canEnroll": true,
			"courses": [
				{
					"title": "Assegnato - PROGETTAZIONE DELL'ARCHITETTURA - TAUGHT IN ENGLISH",
					"location": "PIACENZA",
					"position": 0,
					"canEnroll": true
				}
			],
			"result": 21.7,
			"sectionsResults": null,
			"ofa": {
				"ENG": true
			}
		},
		{
			"id": "",
			"position": 18,
			"canEnroll": true,
			"courses": [
				{
					"title": "Assegnato - PROGETTAZIONE DELL'ARCHITETTURA - TAUGHT IN ENGLISH",
					"location": "PIACENZA",
					"position": 0,
					"canEnroll": true
				}
			],
			"result": 21.5,
			"sectionsResults": null,
			"ofa": {
				"ENG": true
			}
		},
		{
			"id": "",
			"position": 19,
			"canEnroll": false,
			"courses": [],
			"result": 21.1,
			"sectionsResults": null,
			"ofa": {
				"ENG": true
			}
		},
		{
			"id": "",
			"position": 20,
			"canEnroll": false,
			"courses": [],
			"result": 20.9,
			"sectionsResults": null,
			"ofa": {
				"ENG": false
			}
		},
		{
			"id": "",
			"position": 21,
			"canEnroll": false,
			"courses": [],
			"result": 20.8,
			"sectionsResults": null,
			"ofa": {
				"ENG": true
			}
		},
		{
			"id": "",
			"position": 22,
			"canEnroll": false,
			"courses": [],
			"result": 20.7,
			"sectionsResults": null,
			"ofa": {
				"ENG": true
			}
		},
		{
			"id": "",
			"position": 23,
			"canEnroll": true,
			"courses": [
				{
					"title": "Assegnato - PROGETTAZIONE DELL'ARCHITETTURA - TAUGHT IN ENGLISH",
					"location": "PIACENZA",
					"position": 0,
					"canEnroll": true
				}
			],
			"result": 20.5,
			"sectionsResults": null,
			"ofa": {
				"ENG": true
			}
		},
		{
			"id": "",
			"position": 24,
			"canEnroll": false,
			"courses": [],
			"result": 20,
			"sectionsResults": null,
			"ofa": {
				"ENG": true
			}
		},
		{
			"id": "",
			"position": 25,
			"canEnroll": true,
			"courses": [
				{
					"title": "Assegnato - PROGETTAZIONE DELL'ARCHITETTURA - TAUGHT IN ENGLISH",
					"location": "PIACENZA",
					"position": 0,
					"canEnroll": true
				}
			],
			"result": 19.8,
			"sectionsResults": null,
			"ofa": {
				"ENG": true
			}
		},
		{
			"id": "",
			"position": 26,
			"canEnroll": true,
			"courses": [
				{
					"title": "Assegnato - PROGETTAZIONE DELL'ARCHITETTURA - TAUGHT IN ENGLISH",
					"location": "PIACENZA",
					"position": 0,
					"canEnroll": true
				}
			],
			"result": 19.5,
			"sectionsResults": null,
			"ofa": {
				"ENG": true
			}
		},
		{
			"id": "",
			"position": 27,
			"canEnroll": false,
			"courses": [],
			"result": 19.5,
			"sectionsResults": null,
			"ofa": {
				"ENG": true
			}
		},
		{
			"id": "",
			"position": 28,
			"canEnroll": true,
			"courses": [
				{
					"title": "Assegnato - PROGETTAZIONE DELL'ARCHITETTURA - TAUGHT IN ENGLISH",
					"location": "PIACENZA",
					"position": 0,
					"canEnroll": true
				}
			],
			"result": 19.1,
			"sectionsResults": null,
			"ofa": {
				"ENG": true
			}
		},
		{
			"id": "",
			"position": 29,
			"canEnroll": true,
			"courses": [
				{
					"title": "Assegnato - PROGETTAZIONE DELL'ARCHITETTURA - TAUGHT IN ENGLISH",
					"location": "PIACENZA",
					"position": 0,
					"canEnroll": true
				}
			],
			"result": 18.9,
			"sectionsResults": null,
			"ofa": {
				"ENG": true
			}
		},
		{
			"id": "",
			"position": 30,
			"canEnroll": false,
			"courses": [],
			"result": 18.4,
			"sectionsResults": null,
			"ofa": {
				"ENG": true
			}
		},
		{
			"id": "",
			"position": 31,
			"canEnroll": true,
			"courses": [
				{
					"title": "Assegnato - PROGETTAZIONE DELL'ARCHITETTURA - TAUGHT IN ENGLISH",
					"location": "PIACENZA",
					"position": 0,
					"canEnroll": true
				}
			],
			"result": 18,
			"sectionsResults": null,
			"ofa": {
				"ENG": true
			}
		},
		{
			"id": "",
			"position": 32,
			"canEnroll": false,
			"courses": [],
			"result": 18,
			"sectionsResults": null,
			"ofa": {
				"ENG": true
			}
		},
		{
			"id": "",
			"position": 33,
			"canEnroll": true,
			"courses": [
				{
					"title": "Assegnato - PROGETTAZIONE DELL'ARCHITETTURA - TAUGHT IN ENGLISH",
					"location": "PIACENZA",
					"position": 0,
					"canEnroll": true
				}
			],
			"result": 17.9,
			"sectionsResults": null,
			"ofa": {
				"ENG": true
			}
		},
		{
			"id": "",
			"position": 34,
			"canEnroll": true,
			"courses": [
				{
					"title": "Assegnato - PROGETTAZIONE DELL'ARCHITETTURA - TAUGHT IN ENGLISH",
					"location": "PIACENZA",
					"position": 0,
					"canEnroll": true
				}
			],
			"result": 17.7,
			"sectionsResults": null,
			"ofa": {
				"ENG": true
			}
		},
		{
			"id": "",
			"position": 35,
			"canEnroll": true,
			"courses": [
				{
					"title": "Assegnato - PROGETTAZIONE DELL'ARCHITETTURA - TAUGHT IN ENGLISH",
					"location": "PIACENZA",
					"position": 0,
					"canEnroll": true
				}
			],
			"result": 17.5,
			"sectionsResults": null,
			"ofa": {
				"ENG": true
			}
		},
		{
			"id": "",
			"position": 36,
			"canEnroll": true,
			"courses": [
				{
					"title": "Assegnato - PROGETTAZIONE DELL'ARCHITETTURA - TAUGHT IN ENGLISH",
					"location": "PIACENZA",
					"position": 0,
					"canEnroll": true
				}
			],
			"result": 17.4,
			"sectionsResults": null,
			"ofa": {
				"ENG": true
			}
		},
		{
			"id": "",
			"position": 37,
			"canEnroll": false,
			"courses": [],
			"result": 17.3,
			"sectionsResults": null,
			"ofa": {
				"ENG": true
			}
		},
		{
			"id": "",
			"position": 38,
			"canEnroll": false,
			"courses": [],
			"result": 17.2,
			"sectionsResults": null,
			"ofa": {
				"ENG": true
			}
		},
		{
			"id": "",
			"position": 39,
			"canEnroll": true,
			"courses": [
				{
					"title": "Assegnato - PROGETTAZIONE DELL'ARCHITETTURA - TAUGHT IN ENGLISH",
					"location": "PIACENZA",
					"position": 0,
					"canEnroll": true
				}
			],
			"result": 16.2,
			"sectionsResults": null,
			"ofa": {
				"ENG": true
			}
		},
		{
			"id": "",
			"position": 40,
			"canEnroll": true,
			"courses": [
				{
					"title": "PROGETTAZIONE DELL'ARCHITETTURA",
					"location": "PIACENZA",
					"position": 0,
					"canEnroll": true
				}
			],
			"result": 16.1,
			"sectionsResults": null,
			"ofa": {
				"ENG": true
			}
		},
		{
			"id": "",
			"position": 41,
			"canEnroll": true,
			"courses": [
				{
					"title": "Assegnato - PROGETTAZIONE DELL'ARCHITETTURA - TAUGHT IN ENGLISH",
					"location": "PIACENZA",
					"position": 0,
					"canEnroll": true
				}
			],
			"result": 16,
			"sectionsResults": null,
			"ofa": {
				"ENG": true
			}
		},
		{
			"id": "",
			"position": 42,
			"canEnroll": false,
			"courses": [],
			"result": 16,
			"sectionsResults": null,
			"ofa": {
				"ENG": true
			}
		},
		{
			"id": "",
			"position": 43,
			"canEnroll": false,
			"courses": [],
			"result": 15.7,
			"sectionsResults": null,
			"ofa": {
				"ENG": true
			}
		},
		{
			"id": "",
			"position": 44,
			"canEnroll": false,
			"courses": [],
			"result": 15.7,
			"sectionsResults": null,
			"ofa": {
				"ENG": true
			}
		},
		{
			"id": "",
			"position": 45,
			"canEnroll": false,
			"courses": [],
			"result": 15.6,
			"sectionsResults": null,
			"ofa": {
				"ENG": true
			}
		},
		{
			"id": "",
			"position": 46,
			"canEnroll": false,
			"courses": [],
			"result": 15.5,
			"sectionsResults": null,
			"ofa": {
				"ENG": true
			}
		},
		{
			"id": "",
			"position": 47,
			"canEnroll": false,
			"courses": [],
			"result": 15.5,
			"sectionsResults": null,
			"ofa": {
				"ENG": true
			}
		},
		{
			"id": "",
			"position": 48,
			"canEnroll": false,
			"courses": [],
			"result": 15.4,
			"sectionsResults": null,
			"ofa": {
				"ENG": true
			}
		},
		{
			"id": "",
			"position": 49,
			"canEnroll": false,
			"courses": [],
			"result": 15.3,
			"sectionsResults": null,
			"ofa": {
				"ENG": true
			}
		},
		{
			"id": "",
			"position": 50,
			"canEnroll": false,
			"courses": [],
			"result": 15,
			"sectionsResults": null,
			"ofa": {
				"ENG": true
			}
		},
		{
			"id": "",
			"position": 51,
			"canEnroll": false,
			"courses": [],
			"result": 14.9,
			"sectionsResults": null,
			"ofa": {
				"ENG": true
			}
		},
		{
			"id": "",
			"position": 52,
			"canEnroll": false,
			"courses": [],
			"result": 14.7,
			"sectionsResults": null,
			"ofa": {
				"ENG": true
			}
		},
		{
			"id": "",
			"position": 53,
			"canEnroll": false,
			"courses": [],
			"result": 14.5,
			"sectionsResults": null,
			"ofa": {
				"ENG": true
			}
		},
		{
			"id": "",
			"position": 54,
			"canEnroll": false,
			"courses": [],
			"result": 14.4,
			"sectionsResults": null,
			"ofa": {
				"ENG": false
			}
		},
		{
			"id": "",
			"position": 55,
			"canEnroll": false,
			"courses": [],
			"result": 13.5,
			"sectionsResults": null,
			"ofa": {
				"ENG": true
			}
		},
		{
			"id": "",
			"position": 56,
			"canEnroll": false,
			"courses": [],
			"result": 13.4,
			"sectionsResults": null,
			"ofa": {
				"ENG": true
			}
		},
		{
			"id": "",
			"position": 57,
			"canEnroll": false,
			"courses": [],
			"result": 13.3,
			"sectionsResults": null,
			"ofa": {
				"ENG": true
			}
		},
		{
			"id": "",
			"position": 58,
			"canEnroll": false,
			"courses": [],
			"result": 12.4,
			"sectionsResults": null,
			"ofa": {
				"ENG": true
			}
		},
		{
			"id": "",
			"position": 59,
			"canEnroll": false,
			"courses": [],
			"result": 11.7,
			"sectionsResults": null,
			"ofa": {
				"ENG": true
			}
		},
		{
			"id": "",
			"position": 60,
			"canEnroll": false,
			"courses": [],
			"result": 11.7,
			"sectionsResults": null,
			"ofa": {
				"ENG": true
			}
		},
		{
			"id": "",
			"position": 61,
			"canEnroll": false,
			"courses": [],
			"result": 11.6,
			"sectionsResults": null,
			"ofa": {
				"ENG": true
			}
		},
		{
			"id": "",
			"position": 62,
			"canEnroll": false,
			"courses": [],
			"result": 11.5,
			"sectionsResults": null,
			"ofa": {
				"ENG": true
			}
		},
		{
			"id": "",
			"position": 63,
			"canEnroll": false,
			"courses": [],
			"result": 11.1,
			"sectionsResults": null,
			"ofa": {
				"ENG": true
			}
		},
		{
			"id": "",
			"position": 64,
			"canEnroll": false,
			"courses": [],
			"result": 11.1,
			"sectionsResults": null,
			"ofa": {
				"ENG": true
			}
		},
		{
			"id": "",
			"position": 65,
			"canEnroll": false,
			"courses": [],
			"result": 11.1,
			"sectionsResults": null,
			"ofa": {
				"ENG": true
			}
		},
		{
			"id": "",
			"position": 66,
			"canEnroll": false,
			"courses": [],
			"result": 10.6,
			"sectionsResults": null,
			"ofa": {
				"ENG": true
			}
		},
		{
			"id": "",
			"position": 67,
			"canEnroll": false,
			"courses": [],
			"result": 10,
			"sectionsResults": null,
			"ofa": {
				"ENG": true
			}
		},
		{
			"id": "",
			"position": 68,
			"canEnroll": false,
			"courses": [],
			"result": 9.9,
			"sectionsResults": null,
			"ofa": {
				"ENG": true
			}
		},
		{
			"id": "",
			"position": 69,
			"canEnroll": false,
			"courses": [],
			"result": 9.7,
			"sectionsResults": null,
			"ofa": {
				"ENG": true
			}
		},
		{
			"id": "",
			"position": 70,
			"canEnroll": false,
			"courses": [],
			"result": 9.6,
			"sectionsResults": null,
			"ofa": {
				"ENG": true
			}
		},
		{
			"id": "",
			"position": 71,
			"canEnroll": false,
			"courses": [],
			"result": 9.5,
			"sectionsResults": null,
			"ofa": {
				"ENG": true
			}
		},
		{
			"id": "",
			"position": 72,
			"canEnroll": false,
			"courses": [],
			"result": 9.5,
			"sectionsResults": null,
			"ofa": {
				"ENG": true
			}
		},
		{
			"id": "",
			"position": 73,
			"canEnroll": false,
			"courses": [],
			"result": 9.4,
			"sectionsResults": null,
			"ofa": {
				"ENG": false
			}
		},
		{
			"id": "",
			"position": 74,
			"canEnroll": false,
			"courses": [],
			"result": 8.7,
			"sectionsResults": null,
			"ofa": {
				"ENG": true
			}
		},
		{
			"id": "",
			"position": 75,
			"canEnroll": false,
			"courses": [],
			"result": 8.5,
			"sectionsResults": null,
			"ofa": {
				"ENG": true
			}
		},
		{
			"id": "",
			"position": 76,
			"canEnroll": false,
			"courses": [],
			"result": 6.8,
			"sectionsResults": null,
			"ofa": {
				"ENG": true
			}
		},
		{
			"id": "",
			"position": 77,
			"canEnroll": false,
			"courses": [],
			"result": 6.3,
			"sectionsResults": null,
			"ofa": {
				"ENG": true
			}
		},
		{
			"id": "",
			"position": 78,
			"canEnroll": false,
			"courses": [],
			"result": 6.2,
			"sectionsResults": null,
			"ofa": {
				"ENG": true
			}
		},
		{
			"id": "",
			"position": 79,
			"canEnroll": false,
			"courses": [],
			"result": 6.1,
			"sectionsResults": null,
			"ofa": {
				"ENG": true
			}
		},
		{
			"id": "",
			"position": 80,
			"canEnroll": false,
			"courses": [],
			"result": 5,
			"sectionsResults": null,
			"ofa": {
				"ENG": true
			}
		},
		{
			"id": "",
			"position": 81,
			"canEnroll": false,
			"courses": [],
			"result": 4.3,
			"sectionsResults": null,
			"ofa": {
				"ENG": true
			}
		},
		{
			"id": "",
			"position": 82,
			"canEnroll": false,
			"courses": [],
			"result": 4.2,
			"sectionsResults": null,
			"ofa": {
				"ENG": true
			}
		},
		{
			"id": "",
			"position": 83,
			"canEnroll": false,
			"courses": [],
			"result": 3.6,
			"sectionsResults": null,
			"ofa": {
				"ENG": true
			}
		},
		{
			"id": "",
			"position": 84,
			"canEnroll": false,
			"courses": [],
			"result": 3.1,
			"sectionsResults": null,
			"ofa": {
				"ENG": true
			}
		}
	]
}